koffisortwork/__init__.py
koffisortwork/bubble_sort.py
koffisortwork/insertion_sort.py
koffisortwork/quick_sort.py
koffisortwork/selection_sort.py
koffisortwork-0.1.dist-info/METADATA
koffisortwork-0.1.dist-info/WHEEL
koffisortwork-0.1.dist-info/top_level.txt
koffisortwork-0.1.dist-info/RECORD
